tshu-0.1.3.dist-info/METADATA
tshu-0.1.3.dist-info/WHEEL
tshu-0.1.3.dist-info/licenses/LICENSE
tshu/__init__.py
tshu/_command.py
tshu/_command_error.py
tshu/_completed_command.py
tshu/py.typed
tshu/tshu.cpython-314-arm-linux-gnueabihf.so
tshu-0.1.3.dist-info/RECORD
