Metadata-Version: 2.4
Name: tshu
Version: 0.1.3
Requires-Dist: cffi>=1.17.1
License-File: LICENSE
Summary: Run safe and cross-platform bash commands using Python 3.14's t-strings
Keywords: t-strings,bash,shell,sh
Author-email: Priyanshu Dangare <aspizu@protonmail.com>
License-Expression: MIT
Requires-Python: >=3.14b4
Project-URL: Homepage, https://github.com/aspizu/tshu
Project-URL: Documentation, https://aspizu.github.io/tshu/
Project-URL: Repository, https://github.com/aspizu/tshu
Project-URL: Issues, https://github.com/aspizu/tshu/issues
